datamodel_analysisor/__init__.py
datamodel_analysisor/datamodel_analysisor.py
datamodel_analysisor/xml_models.py
datamodel_analysisor-1.0.2.dist-info/METADATA
datamodel_analysisor-1.0.2.dist-info/WHEEL
datamodel_analysisor-1.0.2.dist-info/top_level.txt
datamodel_analysisor-1.0.2.dist-info/RECORD
